stix2validator/__init__.py
stix2validator/codes.py
stix2validator/errors.py
stix2validator/output.py
stix2validator/util.py
stix2validator/validator.py
stix2validator/version.py
stix2validator/schemas-2.0/examples/indicator-for-c2-ip-address.json
stix2validator/schemas-2.0/examples/indicator-to-campaign-relationship.json
stix2validator/schemas-2.0/examples/indicators-for-C2-with-COA.json
stix2validator/schemas-2.0/examples/malicious-email-indicator-with-attachment.json
stix2validator/schemas-2.0/examples/threat-reports/apt1.json
stix2validator/schemas-2.0/examples/threat-reports/poisonivy.json
stix2validator/schemas-2.0/schemas/common/binary.json
stix2validator/schemas-2.0/schemas/common/bundle.json
stix2validator/schemas-2.0/schemas/common/core.json
stix2validator/schemas-2.0/schemas/common/cyber-observable-core.json
stix2validator/schemas-2.0/schemas/common/dictionary.json
stix2validator/schemas-2.0/schemas/common/external-reference.json
stix2validator/schemas-2.0/schemas/common/granular-marking.json
stix2validator/schemas-2.0/schemas/common/hashes-type.json
stix2validator/schemas-2.0/schemas/common/hex.json
stix2validator/schemas-2.0/schemas/common/identifier.json
stix2validator/schemas-2.0/schemas/common/kill-chain-phase.json
stix2validator/schemas-2.0/schemas/common/marking-definition.json
stix2validator/schemas-2.0/schemas/common/timestamp.json
stix2validator/schemas-2.0/schemas/common/url-regex.json
stix2validator/schemas-2.0/schemas/observables/artifact.json
stix2validator/schemas-2.0/schemas/observables/autonomous-system.json
stix2validator/schemas-2.0/schemas/observables/directory.json
stix2validator/schemas-2.0/schemas/observables/domain-name.json
stix2validator/schemas-2.0/schemas/observables/email-addr.json
stix2validator/schemas-2.0/schemas/observables/email-message.json
stix2validator/schemas-2.0/schemas/observables/file.json
stix2validator/schemas-2.0/schemas/observables/ipv4-addr.json
stix2validator/schemas-2.0/schemas/observables/ipv6-addr.json
stix2_validator-3.2.0.dist-info/LICENSE
stix2_validator-3.2.0.dist-info/METADATA
stix2_validator-3.2.0.dist-info/WHEEL
stix2_validator-3.2.0.dist-info/entry_points.txt
stix2_validator-3.2.0.dist-info/top_level.txt
stix2_validator-3.2.0.dist-info/RECORD
