Metadata-Version: 2.1
Name: stix2-validator
Version: 3.2.0
Summary: APIs and scripts for validating STIX 2.x documents.
Home-page: https://github.com/oasis-open/cti-stix-validator
Author: OASIS Cyber Threat Intelligence Technical Committee
Author-email: cti-users@lists.oasis-open.org
Maintainer: Chris Lenk
Maintainer-email: clenk@mitre.org
License: UNKNOWN
Project-URL: Documentation, https://stix2-validator.readthedocs.io/
Project-URL: Source Code, https://github.com/oasis-open/cti-stix-validator/
Project-URL: Bug Tracker, https://github.com/oasis-open/cti-stix-validator/issues/
Keywords: stix stix2 json validation validator stix-validator stix2-validator
Platform: UNKNOWN
Classifier: Development Status :: 4 - Beta
Classifier: Topic :: Security
Classifier: License :: OSI Approved :: BSD License
Classifier: Programming Language :: Python :: 3
Classifier: Programming Language :: Python :: 3.8
Classifier: Programming Language :: Python :: 3.9
Classifier: Programming Language :: Python :: 3.10
Classifier: Programming Language :: Python :: 3.11
Classifier: Programming Language :: Python :: 3.12
Provides-Extra: dev
Provides-Extra: test
Provides-Extra: docs
